verysimple/__init__.py
verysimple/add.py
verysimple/minus.py
verysimple/extras/__init__.py
verysimple/extras/multiply.py
verysimple-0.0.1.dist-info/METADATA
verysimple-0.0.1.dist-info/WHEEL
verysimple-0.0.1.dist-info/top_level.txt
verysimple-0.0.1.dist-info/RECORD
